XinShiqiWoguoXinxijishuChanyeDeFazhan/README.md
XinShiqiWoguoXinxijishuChanyeDeFazhan/__init__.py
XinShiqiWoguoXinxijishuChanyeDeFazhan/__main__.py
XinShiqiWoguoXinxijishuChanyeDeFazhan/file.pdf
XinShiqiWoguoXinxijishuChanyeDeFazhan/index.html
xin_shiqi_woguo_xinxijishu_chanye_de_fazhan-2024.3.3.0.dist-info/METADATA
xin_shiqi_woguo_xinxijishu_chanye_de_fazhan-2024.3.3.0.dist-info/WHEEL
xin_shiqi_woguo_xinxijishu_chanye_de_fazhan-2024.3.3.0.dist-info/entry_points.txt
xin_shiqi_woguo_xinxijishu_chanye_de_fazhan-2024.3.3.0.dist-info/top_level.txt
xin_shiqi_woguo_xinxijishu_chanye_de_fazhan-2024.3.3.0.dist-info/RECORD
